Metadata-Version: 1.1
Name: click-uwescience
Version: 7.0.1.dev0
Summary: A simple wrapper around optparse for powerful command line utilities.
Home-page: http://github.com/uwescience/click
Author: Armin Ronacher
Author-email: tdbaker@cs.washington.edu;armin.ronacher@active-4.com
License: UNKNOWN
Platform: UNKNOWN
Classifier: License :: OSI Approved :: BSD License
Classifier: Programming Language :: Python
Classifier: Programming Language :: Python :: 3
